fast_impl/__init__.py
fast_impl/_nbdev.py
fast_impl/core.py
fast_impl/transforms.py
fast_impl/visualize.py
fast_impl-0.0.6.dist-info/LICENSE
fast_impl-0.0.6.dist-info/METADATA
fast_impl-0.0.6.dist-info/WHEEL
fast_impl-0.0.6.dist-info/entry_points.txt
fast_impl-0.0.6.dist-info/top_level.txt
fast_impl-0.0.6.dist-info/RECORD
