Metadata-Version: 2.1
Name: fast-impl
Version: 0.0.6
Summary: Baseline implementations for various Deep Learning Applications using `fastai2`
Home-page: https://github.com/Kshitij09/fast_impl
Author: Kshitij Patil
Author-email: kshitijpatil98@gmail.com
License: Apache Software License 2.0
Keywords: deep-learning computer-vision fastai2
Platform: UNKNOWN
Classifier: Development Status :: 3 - Alpha
Classifier: Intended Audience :: Developers
Classifier: License :: OSI Approved :: Apache Software License
Classifier: Natural Language :: English
Classifier: Programming Language :: Python :: 3.6
Classifier: Programming Language :: Python :: 3.7
Classifier: Programming Language :: Python :: 3.8
Requires-Python: >=3.6
Requires-Dist: fastai2
Requires-Dist: timm
